{
	"metaDataVersion": "1.0.0",
	"category": "com.microchip.ide.project",
	"content": {
		"metaDataVersion": "1.1.0",
		"name": "com.microchip.mcu32.mplabx.project.csp_apps_sam_c20_c21_ac_wav_gen",
		"version": "3.4.0",
		"displayName": "AC PWM generation Example for SAM C20/C21 Family",
		"projectName": "ac_wav_gen_sam_c21n_xpro",
		"shortDescription": "This example application shows how to use the Analog Comparator Peripheral library to generate a 1KHz PWM waveform.",
		"ide": {
			"name": "MPLABX",
			"semverRange": ">=6.5.0"
		},
		"compiler": [
			{
				"name": "XC32",
				"semverRange": ">=4.21.0"
			}
		],
		"dfp": {
			"name": "SAMC21_DFP",
			"semverRange": "^3.8.119"
		},
		"configurator": {
			"name": "MCC",
			"semverRange": ">=5.3.0"
		},
		"device": {
			"metaDataVersion": "1.0.0",
			"category": "com.microchip.portal.contentRef",
			"content": {
				"metaDataVersion": "1.0.0",
				"category": "com.microchip.device",
				"name": "ATSAMC21N18A",
				"versionRange": "*"
			}
		},
		"author": "Microchip",
		"subcategories": [
			[
				"Development Kit",
				"SAMC21N Xplained Pro Evaluation Kit"
			],
			[
				"Harmony",
				"Peripherals",
				"AC"
			],
			[
				"Peripherals",
				"AC"
			]
		],
		"peripherals": [
			"AC"
		],
		"keywords": [
			"MHC",
			"Harmony",
			"ATSAMC21N18A",
			"SAM C20/C21 Family",
			"AC voltage",
			"AC",
			"Analog Comparator",
			"Comparator",
			"Analog"
		],
		"additionalData": {
			"longDescription": {
				"metaDataVersion": "1.0.0",
				"category": "com.microchip.portal.fileRef",
				"content": {
					"metaDataVersion": "1.0.0",
					"fileName": "./../../readme.md",
					"mimeType": "text/markdown"
				}
			}
		}
	}
}